papillon.py
papillon-0.2.0.dist-info/METADATA
papillon-0.2.0.dist-info/RECORD
papillon-0.2.0.dist-info/WHEEL
papillon-0.2.0.dist-info/top_level.txt
