Metadata-Version: 2.1
Name: papillon
Version: 0.2.0
Summary: A Python module to read and plot (cuffdiff) Galaxy RNA-seq data
Home-page: https://github.com/domenico-somma/Papillon/
Author: Domenico Somma
Author-email: domenico.somma@glasgow.ac.uk
License: Mozilla Public License 2.0
Platform: UNKNOWN
Requires-Python: >=3.3, <4
Requires-Dist: pandas (>=0.23)
Requires-Dist: Seaborn (>=0.8.1)
